{
    "firsatlar": [
        {
            "id": "n8govhcajbs21f8s3unge1",
            "name": "Bebedor Silikon Damaklı Emzik 2'li",
            "store": "Civil",
            "price": "99 TL",
            "discountBadge": "Süper Fiyat",
            "icon": "🍼",
            "buyUrl": "https://www.civil.com"
        },
        {
            "id": "oykeovadhhntwg628zm1m",
            "name": "Sleepy Bio Natural Bebek Bezi",
            "store": "Trendyol",
            "price": "244 TL",
            "discountBadge": "En Ucuz Fiyat",
            "icon": "🍼",
            "imageUrl": "https://cdn.dsmcdn.com/ty953/product/media/images/20230620/15/384729104/850192834_1_org_zoom.jpg",
            "buyUrl": "https://www.trendyol.com"
        },
        {
            "id": "d8csjia3jeg19wiuntwd7v",
            "name": "Pilsan Pratik Mama Sandalyesi",
            "store": "Hepsiburada",
            "price": "549 TL",
            "discountBadge": "Flaş İndirim",
            "icon": "🪑",
            "buyUrl": "https://www.hepsiburada.com"
        },
        {
            "id": "rtcjj3jhpkfszvusi3ul4",
            "name": "Carter's Organik Pamuk Tulum",
            "store": "Amazon",
            "price": "469 TL",
            "discountBadge": "Flaş İndirim",
            "icon": "👶",
            "buyUrl": "https://www.amazon.com"
        }
    ]
}